setup.cfg
setup.py
pyramid_utils/__init__.py
pyramid_utils.egg-info/PKG-INFO
pyramid_utils.egg-info/SOURCES.txt
pyramid_utils.egg-info/dependency_links.txt
pyramid_utils.egg-info/entry_points.txt
pyramid_utils.egg-info/not-zip-safe
pyramid_utils.egg-info/requires.txt
pyramid_utils.egg-info/top_level.txt