Metadata-Version: 1.0
Name: pyramid-utils
Version: 0.0dev
Summary: Module that adds some plugins to speed up writting pyramid applications
Home-page: UNKNOWN
Author: Loic Faure-Lacroix
Author-email: lamerstar@gmail.com
License: MIT
Platform: UNKNOWN
